theoneapi/__init__.py
theoneapi/client.py
theoneapi/entity/__init__.py
theoneapi/entity/movie.py
theoneapi/entity/quote.py
theoneapi/query/__init__.py
theoneapi-0.0.1.dist-info/LICENSE
theoneapi-0.0.1.dist-info/METADATA
theoneapi-0.0.1.dist-info/WHEEL
theoneapi-0.0.1.dist-info/top_level.txt
theoneapi-0.0.1.dist-info/RECORD
