Metadata-Version: 2.1
Name: theoneapi
Version: 0.0.1
Summary: This SDK provides (partial) access to LibLab's Lord of the Rings API - The One API to rule them all.
Home-page: https://github.com/raffykaloustian/raffy_kaloustian-SDK
Author: Raffy Kaloustian
Author-email: raffykaloustian@email.com
License: MIT
Keywords: liblab,sdk,api
Classifier: Development Status :: 5 - Production/Stable
Classifier: Intended Audience :: Developers
Classifier: License :: OSI Approved :: MIT License
Classifier: Operating System :: OS Independent
Classifier: Programming Language :: Python
Classifier: Programming Language :: Python :: 3.9
Classifier: Programming Language :: Python :: 3.10
Classifier: Programming Language :: Python :: 3.11
Classifier: Topic :: Software Development :: Libraries :: Python Modules
Requires-Python: >=3.9
License-File: LICENSE
Requires-Dist: certifi (==2022.12.7)
Requires-Dist: charset-normalizer (==3.1.0)
Requires-Dist: idna (==3.4)
Requires-Dist: requests (==2.30.0)
Requires-Dist: urllib3 (==2.0.2)
